EpicGames_FreeGames_Bot/EpicGamesAutomationApp.py
EpicGames_FreeGames_Bot/EpicGamesConnect.py
EpicGames_FreeGames_Bot/WaitHelper.py
EpicGames_FreeGames_Bot/WebDriverHelper.py
EpicGames_FreeGames_Bot/__init__.py
EpicGames_FreeGames_Bot/main.py
EpicGames_FreeGames_Bot-0.6.dist-info/METADATA
EpicGames_FreeGames_Bot-0.6.dist-info/WHEEL
EpicGames_FreeGames_Bot-0.6.dist-info/entry_points.txt
EpicGames_FreeGames_Bot-0.6.dist-info/top_level.txt
EpicGames_FreeGames_Bot-0.6.dist-info/RECORD
