Metadata-Version: 2.1
Name: EpicGames-FreeGames-Bot
Version: 0.6
Requires-Dist: selenium
Requires-Dist: beautifulsoup4
